erabytse_veil/__init__.py
erabytse_veil/veil.py
erabytse_veil-0.1.0.dist-info/licenses/LICENSE
erabytse_veil-0.1.0.dist-info/METADATA
erabytse_veil-0.1.0.dist-info/WHEEL
erabytse_veil-0.1.0.dist-info/entry_points.txt
erabytse_veil-0.1.0.dist-info/top_level.txt
erabytse_veil-0.1.0.dist-info/RECORD
