Metadata-Version: 2.4
Name: erabytse-veil
Version: 0.1.0
Summary: An ethical veil for image metadata — not deletion, but intentional protection.
Author-email: takouzlo <f.bfalik@gmail.com>
License: MIT
Requires-Python: >=3.8
License-File: LICENSE
Requires-Dist: Pillow>=9.0.0
Dynamic: license-file
